expyvalidations/__init__.py
expyvalidations/config.py
expyvalidations/exceptions.py
expyvalidations/utils.py
expyvalidations/excel/__init__.py
expyvalidations/excel/excel.py
expyvalidations/excel/models.py
expyvalidations/validations/__init__.py
expyvalidations/validations/bool.py
expyvalidations/validations/cel.py
expyvalidations/validations/cpf.py
expyvalidations/validations/date.py
expyvalidations/validations/duplications.py
expyvalidations/validations/email.py
expyvalidations/validations/float.py
expyvalidations/validations/int.py
expyvalidations/validations/sex.py
expyvalidations/validations/string.py
expyvalidations/validations/time.py
expyvalidations-0.0.4.dist-info/LICENSE
expyvalidations-0.0.4.dist-info/METADATA
expyvalidations-0.0.4.dist-info/WHEEL
expyvalidations-0.0.4.dist-info/top_level.txt
expyvalidations-0.0.4.dist-info/RECORD
