Metadata-Version: 2.1
Name: expyvalidations
Version: 0.0.4
Summary: Sheets data validation
Home-page: https://github.com/exebixel/expyvalidations
Author: exebixel
Author-email: ezequielnat7@gmail.com
License: MIT
Project-URL: Documentation, https://github.com/exebixel/expyvalidations/wiki
Project-URL: Source, https://github.com/exebixel/expyvalidations
Platform: UNKNOWN
Classifier: Operating System :: OS Independent
Classifier: Environment :: Console
Classifier: Intended Audience :: Developers
Classifier: Topic :: Software Development :: Libraries
Classifier: License :: OSI Approved :: MIT License
Classifier: Programming Language :: Python
Classifier: Programming Language :: Python :: 3
Classifier: Programming Language :: Python :: 3.7
Classifier: Programming Language :: Python :: 3.8
Requires-Python: >=3.7
License-File: LICENSE
Requires-Dist: alive-progress (>=2.4.1)
Requires-Dist: openpyxl
Requires-Dist: pandas (>=1.4.0)
Requires-Dist: xlrd
